{
  "updated_at": "2026-05-03T07:22:23.802757+00:00",
  "tickers": [
    {
      "ticker": "NVDA",
      "price": 198.42,
      "change_pct": -1.42,
      "series": [
        201.63,
        201.6,
        201.93,
        200.29,
        199.19,
        200.46,
        199.69,
        200.17,
        199.98,
        200.03,
        199.75,
        199.3,
        197.57,
        198.69,
        199.28,
        199.82,
        199.7,
        199.53,
        199.62,
        199.4,
        199.47,
        199.55,
        199.15,
        198.93,
        198.82,
        199.19,
        199.56,
        199.64,
        199.23,
        199.13,
        199.04,
        198.6,
        198.93,
        199.01,
        199.17,
        198.65,
        198.82,
        198.96,
        198.65,
        198.91,
        199.27,
        199.16,
        199.35,
        199.62,
        199.84,
        200.12,
        199.89,
        199.85,
        199.96,
        200.09,
        200.07,
        199.93,
        199.94,
        199.65,
        199.29,
        199.51,
        199.2,
        199.14,
        199.29,
        199.13,
        198.97,
        198.82,
        198.62,
        198.43,
        198.42,
        198.35,
        198.45,
        198.65,
        199.02,
        199.4,
        199.66,
        199.71,
        199.85,
        199.7,
        199.6,
        199.16,
        199.04,
        198.42
      ],
      "status": "ok"
    },
    {
      "ticker": "MU",
      "price": 542.32,
      "change_pct": 5.97,
      "series": [
        513.82,
        524.1,
        529.62,
        532.64,
        536.63,
        541.45,
        543.77,
        544.77,
        543.0,
        539.75,
        542.3,
        542.06,
        536.4,
        537.58,
        536.0,
        532.88,
        530.36,
        527.66,
        527.23,
        528.38,
        530.02,
        533.55,
        531.59,
        530.16,
        532.09,
        532.85,
        530.35,
        529.47,
        530.89,
        531.99,
        531.8,
        532.14,
        531.19,
        532.1,
        531.15,
        529.55,
        530.02,
        532.73,
        533.53,
        533.92,
        532.92,
        531.0,
        531.35,
        530.96,
        530.51,
        531.29,
        530.76,
        530.01,
        529.88,
        528.63,
        531.28,
        535.16,
        534.89,
        535.78,
        534.84,
        538.77,
        537.94,
        540.45,
        540.37,
        540.89,
        541.79,
        539.26,
        539.08,
        537.48,
        538.93,
        540.12,
        538.78,
        539.21,
        539.19,
        538.96,
        541.27,
        541.38,
        541.7,
        540.94,
        541.59,
        541.0,
        542.04,
        542.32
      ],
      "status": "ok"
    },
    {
      "ticker": "SNDK",
      "price": 1188.16,
      "change_pct": 12.19,
      "series": [
        1063.65,
        1071.9,
        1110.69,
        1114.44,
        1112.2,
        1141.13,
        1149.89,
        1138.29,
        1142.0,
        1128.78,
        1130.58,
        1120.14,
        1102.32,
        1099.0,
        1100.32,
        1092.9,
        1085.4,
        1078.0,
        1088.04,
        1088.49,
        1092.82,
        1105.37,
        1098.99,
        1098.29,
        1103.37,
        1098.08,
        1089.5,
        1092.31,
        1099.01,
        1099.03,
        1102.0,
        1106.9,
        1101.35,
        1099.99,
        1100.63,
        1098.3,
        1105.36,
        1102.9,
        1099.34,
        1107.98,
        1106.0,
        1102.08,
        1101.32,
        1099.28,
        1095.18,
        1099.58,
        1099.0,
        1098.22,
        1100.14,
        1099.5,
        1103.6,
        1107.07,
        1107.61,
        1109.62,
        1107.8,
        1115.64,
        1114.58,
        1123.48,
        1133.0,
        1131.46,
        1140.0,
        1139.0,
        1137.01,
        1129.02,
        1137.23,
        1146.77,
        1144.0,
        1143.73,
        1150.25,
        1148.66,
        1149.1,
        1153.22,
        1152.02,
        1150.0,
        1161.38,
        1167.91,
        1174.55,
        1188.16
      ],
      "status": "ok"
    },
    {
      "ticker": "ANET",
      "price": 172.76,
      "change_pct": -0.13,
      "series": [
        175.39,
        176.73,
        176.83,
        176.19,
        176.15,
        176.58,
        176.57,
        175.91,
        176.01,
        175.9,
        175.79,
        175.96,
        174.82,
        174.52,
        174.76,
        174.88,
        175.01,
        174.82,
        175.13,
        174.95,
        175.54,
        175.93,
        175.73,
        176.2,
        176.34,
        176.6,
        176.19,
        175.99,
        175.67,
        175.75,
        175.58,
        175.45,
        175.35,
        175.57,
        175.57,
        175.45,
        175.34,
        175.59,
        175.15,
        175.43,
        175.48,
        175.38,
        175.6,
        175.58,
        175.54,
        175.49,
        175.43,
        175.6,
        175.66,
        175.76,
        175.77,
        175.86,
        176.07,
        176.12,
        176.24,
        176.57,
        176.01,
        176.0,
        175.89,
        175.78,
        175.72,
        176.02,
        175.63,
        175.29,
        175.37,
        175.2,
        175.19,
        174.96,
        174.95,
        174.48,
        174.3,
        174.29,
        174.31,
        174.05,
        173.77,
        173.62,
        173.01,
        172.76
      ],
      "status": "ok"
    },
    {
      "ticker": "VRT",
      "price": 328.33,
      "change_pct": -0.7,
      "series": [
        325.64,
        329.32,
        330.45,
        328.92,
        328.95,
        330.84,
        330.7,
        329.52,
        329.41,
        328.4,
        329.21,
        328.97,
        327.86,
        326.07,
        327.57,
        327.2,
        326.99,
        325.8,
        325.61,
        325.87,
        326.28,
        327.52,
        327.96,
        328.1,
        328.86,
        329.25,
        329.41,
        329.58,
        328.68,
        328.82,
        328.9,
        328.45,
        328.42,
        329.08,
        328.39,
        327.58,
        328.02,
        328.39,
        328.32,
        328.89,
        329.86,
        329.88,
        330.11,
        329.96,
        329.93,
        329.29,
        329.07,
        329.12,
        329.11,
        328.86,
        329.19,
        329.21,
        329.64,
        329.77,
        329.86,
        329.4,
        329.4,
        329.37,
        329.81,
        329.82,
        329.71,
        328.98,
        328.94,
        328.59,
        328.86,
        328.8,
        328.42,
        328.61,
        329.14,
        329.72,
        329.62,
        329.41,
        329.17,
        329.17,
        328.88,
        328.61,
        327.49,
        328.33
      ],
      "status": "ok"
    },
    {
      "ticker": "TSM",
      "price": 397.84,
      "change_pct": 1.12,
      "series": [
        394.91,
        399.99,
        401.6,
        398.52,
        399.04,
        402.52,
        402.8,
        401.12,
        401.23,
        400.68,
        400.45,
        399.08,
        395.67,
        397.06,
        398.56,
        398.37,
        398.19,
        398.06,
        397.83,
        398.36,
        398.4,
        398.95,
        399.39,
        399.23,
        399.14,
        399.02,
        398.89,
        398.46,
        397.83,
        398.48,
        398.47,
        398.36,
        398.4,
        398.95,
        398.44,
        397.77,
        398.11,
        398.33,
        397.83,
        398.1,
        398.43,
        398.21,
        398.01,
        398.18,
        398.17,
        398.46,
        398.38,
        398.67,
        398.83,
        398.58,
        398.85,
        399.2,
        399.52,
        400.08,
        400.01,
        399.78,
        398.74,
        398.52,
        398.43,
        398.42,
        398.33,
        398.7,
        398.27,
        397.87,
        398.11,
        398.28,
        398.5,
        398.61,
        398.21,
        398.89,
        398.96,
        398.93,
        398.4,
        398.36,
        398.62,
        398.61,
        398.65,
        397.84
      ],
      "status": "ok"
    },
    {
      "ticker": "MRVL",
      "price": 164.95,
      "change_pct": 1.6,
      "series": [
        161.82,
        164.01,
        164.0,
        163.76,
        163.3,
        165.11,
        165.05,
        163.74,
        164.5,
        164.37,
        164.7,
        164.43,
        163.3,
        163.52,
        163.49,
        163.1,
        163.42,
        163.0,
        163.28,
        163.43,
        163.84,
        164.69,
        164.63,
        164.6,
        164.74,
        164.9,
        164.68,
        164.61,
        164.69,
        164.96,
        165.21,
        165.27,
        165.36,
        165.81,
        165.26,
        165.14,
        165.33,
        165.35,
        165.1,
        165.42,
        165.6,
        165.42,
        165.66,
        165.71,
        165.92,
        165.84,
        165.56,
        165.48,
        165.63,
        165.77,
        165.82,
        165.97,
        165.6,
        165.51,
        165.54,
        165.79,
        166.09,
        166.09,
        166.1,
        166.11,
        166.12,
        165.85,
        165.6,
        164.82,
        164.75,
        164.79,
        165.02,
        164.92,
        164.88,
        165.03,
        165.29,
        165.37,
        165.26,
        164.86,
        164.79,
        164.48,
        164.87,
        164.95
      ],
      "status": "ok"
    },
    {
      "ticker": "ALAB",
      "price": 202.82,
      "change_pct": 4.01,
      "series": [
        198.87,
        199.67,
        202.32,
        202.18,
        200.8,
        200.07,
        200.85,
        200.57,
        201.73,
        201.17,
        200.09,
        200.79,
        199.19,
        198.83,
        199.39,
        199.91,
        200.03,
        200.9,
        200.09,
        199.95,
        201.09,
        200.88,
        201.41,
        201.49,
        201.78,
        201.98,
        202.93,
        203.59,
        202.26,
        202.63,
        204.45,
        203.58,
        204.16,
        203.98,
        202.91,
        201.78,
        201.88,
        202.21,
        201.18,
        201.65,
        202.31,
        201.73,
        201.9,
        201.98,
        201.53,
        201.52,
        200.88,
        200.26,
        200.56,
        198.48,
        199.57,
        200.24,
        199.9,
        199.2,
        200.12,
        200.75,
        202.0,
        202.15,
        202.6,
        203.11,
        203.12,
        202.27,
        201.71,
        202.09,
        202.03,
        201.87,
        201.62,
        202.69,
        202.58,
        202.0,
        201.53,
        201.55,
        201.15,
        200.73,
        200.91,
        200.89,
        201.49,
        202.82
      ],
      "status": "ok"
    },
    {
      "ticker": "CRDO",
      "price": 184.43,
      "change_pct": 4.93,
      "series": [
        173.82,
        175.88,
        176.5,
        174.87,
        173.68,
        175.59,
        175.68,
        174.78,
        174.87,
        174.35,
        174.73,
        175.63,
        173.0,
        173.0,
        172.81,
        173.13,
        173.91,
        173.62,
        173.21,
        173.13,
        173.14,
        174.3,
        174.46,
        174.97,
        174.22,
        175.2,
        175.62,
        175.91,
        175.85,
        176.27,
        182.06,
        180.51,
        180.53,
        180.91,
        180.1,
        179.54,
        179.79,
        180.33,
        180.1,
        180.11,
        180.51,
        179.95,
        180.52,
        180.73,
        180.91,
        180.97,
        180.7,
        180.63,
        181.19,
        180.07,
        180.43,
        180.91,
        180.65,
        181.11,
        181.3,
        181.49,
        181.72,
        181.71,
        182.36,
        182.38,
        182.1,
        181.88,
        181.89,
        182.34,
        182.22,
        182.15,
        182.25,
        182.7,
        183.12,
        183.13,
        183.0,
        182.82,
        183.5,
        183.68,
        183.8,
        183.43,
        184.55,
        184.43
      ],
      "status": "ok"
    },
    {
      "ticker": "LITE",
      "price": 949.6,
      "change_pct": 4.24,
      "series": [
        954.93,
        966.02,
        970.42,
        966.3,
        954.86,
        962.03,
        961.56,
        954.5,
        954.53,
        949.48,
        961.0,
        963.29,
        956.62,
        953.27,
        961.27,
        962.0,
        960.09,
        960.5,
        964.53,
        969.94,
        971.39,
        975.61,
        975.09,
        974.07,
        975.39,
        981.44,
        977.0,
        976.85,
        977.8,
        978.07,
        976.77,
        971.79,
        969.39,
        970.47,
        968.0,
        965.01,
        966.78,
        968.08,
        969.27,
        973.0,
        974.67,
        972.1,
        972.91,
        970.77,
        966.86,
        967.81,
        967.32,
        969.25,
        966.99,
        965.5,
        966.26,
        965.0,
        965.0,
        965.76,
        966.28,
        965.17,
        965.0,
        965.91,
        965.91,
        961.62,
        961.87,
        959.65,
        955.21,
        952.5,
        951.28,
        950.63,
        953.13,
        950.76,
        948.49,
        949.65,
        948.57,
        950.04,
        950.67,
        948.49,
        947.35,
        948.64,
        949.09,
        949.6
      ],
      "status": "ok"
    },
    {
      "ticker": "COHR",
      "price": 329.68,
      "change_pct": 4.0,
      "series": [
        323.02,
        330.08,
        332.23,
        329.79,
        328.52,
        331.45,
        332.58,
        331.61,
        332.56,
        328.6,
        330.33,
        331.22,
        328.11,
        327.06,
        329.29,
        328.77,
        328.48,
        328.38,
        329.15,
        328.57,
        330.08,
        331.6,
        331.67,
        332.39,
        334.3,
        334.7,
        332.54,
        332.88,
        331.8,
        332.77,
        333.5,
        333.77,
        332.49,
        332.34,
        331.36,
        329.87,
        330.39,
        331.37,
        330.51,
        331.68,
        332.56,
        332.61,
        332.78,
        332.55,
        331.59,
        332.02,
        331.81,
        331.87,
        332.17,
        330.97,
        331.25,
        331.29,
        329.85,
        329.76,
        329.52,
        329.45,
        328.94,
        329.53,
        329.49,
        329.7,
        330.48,
        330.45,
        330.3,
        329.55,
        329.32,
        328.91,
        328.52,
        328.17,
        328.67,
        328.23,
        327.8,
        328.71,
        328.48,
        328.27,
        329.52,
        330.0,
        330.18,
        329.68
      ],
      "status": "ok"
    }
  ],
  "storage_prices": {
    "dram": {
      "source": "TrendForce",
      "url": "https://www.trendforce.com/price/dram",
      "latest_price": null,
      "weekly_growth_pct": null,
      "monthly_growth_pct": null,
      "status": "ok_but_unparsed"
    },
    "nand": {
      "source": "TrendForce",
      "url": "https://www.trendforce.com/price/flash",
      "latest_price": null,
      "weekly_growth_pct": null,
      "monthly_growth_pct": null,
      "status": "ok_but_unparsed"
    }
  },
  "custom_tickers": []
}