{
  "updated_at": "2026-03-17T14:57:07.803393+00:00",
  "tickers": [
    {
      "ticker": "NVDA",
      "price": 183.17,
      "change_pct": -1.02,
      "series": [
        183.53,
        184.01,
        184.05,
        183.88,
        183.44,
        183.09,
        182.57,
        181.93,
        182.38,
        183.01,
        183.46,
        183.09,
        183.08,
        183.08,
        183.16,
        183.14,
        183.09,
        183.17
      ],
      "status": "ok"
    },
    {
      "ticker": "MU",
      "price": 457.76,
      "change_pct": 1.15,
      "series": [
        451.44,
        447.33,
        448.43,
        446.88,
        448.66,
        449.68,
        448.77,
        449.09,
        448.4,
        451.88,
        452.67,
        453.83,
        453.47,
        455.44,
        455.61,
        455.9,
        456.39,
        457.76
      ],
      "status": "ok"
    },
    {
      "ticker": "SNDK",
      "price": 714.84,
      "change_pct": -0.16,
      "series": [
        712.5,
        705.51,
        706.5,
        696.4,
        701.78,
        703.23,
        704.3,
        709.6,
        709.69,
        713.15,
        714.66,
        713.47,
        710.19,
        709.29,
        711.75,
        713.94,
        713.85,
        714.84
      ],
      "status": "ok"
    },
    {
      "ticker": "ANET",
      "price": 134.16,
      "change_pct": -0.63,
      "series": [
        135.65,
        136.2,
        135.65,
        135.25,
        134.62,
        134.52,
        134.97,
        134.9,
        134.68,
        134.34,
        134.18,
        134.04,
        134.41,
        134.14,
        134.26,
        134.48,
        134.05,
        134.16
      ],
      "status": "ok"
    },
    {
      "ticker": "VRT",
      "price": 269.0,
      "change_pct": 3.2,
      "series": [
        265.62,
        267.68,
        267.4,
        267.29,
        267.1,
        268.58,
        267.71,
        268.2,
        268.37,
        268.74,
        268.3,
        268.02,
        267.92,
        266.74,
        267.1,
        269.09,
        268.79,
        269.0
      ],
      "status": "ok"
    },
    {
      "ticker": "TSM",
      "price": 345.05,
      "change_pct": 1.31,
      "series": [
        341.25,
        340.93,
        340.55,
        342.18,
        342.97,
        342.53,
        342.36,
        342.23,
        342.39,
        342.8,
        342.63,
        342.22,
        342.13,
        342.48,
        343.54,
        344.15,
        344.76,
        345.05
      ],
      "status": "ok"
    },
    {
      "ticker": "MRVL",
      "price": 91.89,
      "change_pct": -0.24,
      "series": [
        92.96,
        93.32,
        92.92,
        92.46,
        92.24,
        92.28,
        92.25,
        91.57,
        91.51,
        91.57,
        91.52,
        91.56,
        91.83,
        91.65,
        91.93,
        91.83,
        91.82,
        91.89
      ],
      "status": "ok"
    },
    {
      "ticker": "ALAB",
      "price": 133.54,
      "change_pct": 2.82,
      "series": [
        132.1,
        135.09,
        132.76,
        131.4,
        131.24,
        132.15,
        132.6,
        132.38,
        131.92,
        131.94,
        132.07,
        132.84,
        133.04,
        132.75,
        133.15,
        132.89,
        133.31,
        133.54
      ],
      "status": "ok"
    },
    {
      "ticker": "CRDO",
      "price": 111.22,
      "change_pct": -9.27,
      "series": [
        121.91,
        121.81,
        119.06,
        115.45,
        114.46,
        114.52,
        113.38,
        111.38,
        112.21,
        111.45,
        111.68,
        112.31,
        112.18,
        111.86,
        111.4,
        110.83,
        110.76,
        111.22
      ],
      "status": "ok"
    },
    {
      "ticker": "LITE",
      "price": 639.85,
      "change_pct": 7.32,
      "series": [
        597.97,
        603.85,
        610.03,
        607.36,
        619.0,
        619.8,
        618.79,
        617.07,
        621.39,
        622.28,
        623.78,
        627.95,
        637.04,
        635.75,
        642.88,
        645.61,
        641.0,
        639.85
      ],
      "status": "ok"
    },
    {
      "ticker": "COHR",
      "price": 246.02,
      "change_pct": 4.57,
      "series": [
        235.68,
        238.28,
        240.3,
        239.85,
        241.88,
        244.78,
        243.65,
        244.11,
        245.45,
        245.66,
        244.48,
        244.98,
        246.87,
        245.72,
        247.01,
        248.18,
        245.76,
        246.02
      ],
      "status": "ok"
    }
  ],
  "storage_prices": {
    "dram": {
      "source": "TrendForce",
      "url": "https://www.trendforce.com/price/dram",
      "latest_price": null,
      "weekly_growth_pct": null,
      "monthly_growth_pct": null,
      "status": "ok_but_unparsed"
    },
    "nand": {
      "source": "TrendForce",
      "url": "https://www.trendforce.com/price/flash",
      "latest_price": null,
      "weekly_growth_pct": null,
      "monthly_growth_pct": null,
      "status": "ok_but_unparsed"
    }
  },
  "custom_tickers": []
}